headtailx/__init__.py
headtailx/headtailx_common.py
headtailx/headx.py
headtailx/tailx.py
headtailx-0.0.1.dist-info/LICENSE
headtailx-0.0.1.dist-info/METADATA
headtailx-0.0.1.dist-info/WHEEL
headtailx-0.0.1.dist-info/entry_points.txt
headtailx-0.0.1.dist-info/top_level.txt
headtailx-0.0.1.dist-info/RECORD
