Metadata-Version: 2.1
Name: headtailx
Version: 0.0.1
Summary: Extends `head` and `tail` commands to support previewing binary data formats
Home-page: https://github.com/mitchellpkt/headtailx
Author: Mitchell P. Krawiec-Thayer
Author-email: headtailx@mitchellpkt.com
Classifier: Development Status :: 3 - Alpha
Classifier: Intended Audience :: Developers
Classifier: License :: OSI Approved :: MIT License
Classifier: Operating System :: OS Independent
Classifier: Programming Language :: Python :: 3
Classifier: Programming Language :: Python :: 3.6
Classifier: Programming Language :: Python :: 3.7
Classifier: Programming Language :: Python :: 3.8
Classifier: Programming Language :: Python :: 3.9
Classifier: Programming Language :: Python :: 3.10
Classifier: Programming Language :: Python :: 3.11
Requires-Python: >=3.6
License-File: LICENSE
Requires-Dist: pandas
Requires-Dist: pyarrow
Requires-Dist: openpyxl
Requires-Dist: fastparquet
Requires-Dist: tables
Provides-Extra: test
Requires-Dist: pytest ; extra == 'test'
